threadmanager/__init__.py
threadmanager/classes.py
threadmanager/constants.py
threadmanager/convenience.py
threadmanager/exceptions.py
threadmanager/statistics.py
threadmanager-0.1.0.dist-info/COPYING
threadmanager-0.1.0.dist-info/COPYING.LESSER
threadmanager-0.1.0.dist-info/LICENSE
threadmanager-0.1.0.dist-info/METADATA
threadmanager-0.1.0.dist-info/WHEEL
threadmanager-0.1.0.dist-info/top_level.txt
threadmanager-0.1.0.dist-info/RECORD
