Metadata-Version: 2.1
Name: threadmanager
Version: 0.1.0
Summary: A thread manager for Python programs
Home-page: https://github.com/brandonmpace/threadmanager
Author: Brandon M. Pace
Author-email: brandonmpace@gmail.com
License: GNU Lesser General Public License v3 or later
Keywords: thread state manager
Platform: any
Classifier: Development Status :: 5 - Production/Stable
Classifier: License :: OSI Approved :: GNU Lesser General Public License v3 or later (LGPLv3+)
Classifier: Operating System :: OS Independent
Classifier: Programming Language :: Python :: 3
Requires-Python: >=3.6.5
Requires-Dist: prettytable (>=0.7.2)
